{
    "last_updated": "2026-04-15T11:00:01.174249+00:00",
    "alerts_24h": 24,
    "alerts_last_6h": 8,
    "alerts_previous_6h": 4,
    "trend_direction": "ACCELERATING",
    "alerts_by_type": {
        "NEWS_SIGNAL": 17,
        "SCHEDULED_BET": 7
    },
    "category_breakdown": {
        "geopolitical": 17
    },
    "dominant_category": "geopolitical",
    "scores_24h": {
        "avg": 10.0,
        "max": 12,
        "count": 17
    },
    "open_positions": 19,
    "total_deployed": 103.25
}