{
    "last_updated": "2026-04-06T00:00:01.789469+00:00",
    "alerts_24h": 36,
    "alerts_last_6h": 11,
    "alerts_previous_6h": 10,
    "trend_direction": "STABLE",
    "alerts_by_type": {
        "POSITION_ALERT": 14,
        "NEWS_SIGNAL": 15,
        "SCHEDULED_BET": 5,
        "NEW_BET": 1,
        "POSITION_MATCH": 1
    },
    "category_breakdown": {
        "geopolitical": 14,
        "oil": 1
    },
    "dominant_category": "geopolitical",
    "scores_24h": {
        "avg": 10.3,
        "max": 13,
        "count": 15
    },
    "position_signals": {
        "US x Iran ceasefire by May 31? Yes": {
            "signals_12h": 5,
            "signal_activity": "HIGH"
        },
        "Trump announces end of military operations against Iran by April 30th? Yes": {
            "signals_12h": 1,
            "signal_activity": "LOW"
        },
        "Trump announces end of military operations against Iran by April 15th? No": {
            "signals_12h": 1,
            "signal_activity": "LOW"
        },
        "Israeli forces cross the Litani River by June 30? Yes": {
            "signals_12h": 1,
            "signal_activity": "LOW"
        }
    },
    "open_positions": 21,
    "total_deployed": 122.39
}